kmakepdf/__init__.py
kmakepdf/__main__.py
kmakepdf/cli.py
kmakepdf/converter.py
kmakepdf-0.1.2.dist-info/WHEEL
kmakepdf-0.1.2.dist-info/entry_points.txt
kmakepdf-0.1.2.dist-info/METADATA
kmakepdf-0.1.2.dist-info/RECORD
