Metadata-Version: 2.3
Name: kmakepdf
Version: 0.1.2
Summary: Add your description here
Author: robinbreast
Author-email: robinbreast <robinbreast1412@gmail.com>
Requires-Dist: pillow>=12.0.0
Requires-Dist: pypdf>=6.4.2
Requires-Dist: rich>=13.0.0
Requires-Python: >=3.12
